playwright_mcp/__init__.py
playwright_mcp/server.py
playwright_mcp-0.1.0.dist-info/METADATA
playwright_mcp-0.1.0.dist-info/WHEEL
playwright_mcp-0.1.0.dist-info/entry_points.txt
playwright_mcp-0.1.0.dist-info/RECORD
