Metadata-Version: 2.4
Name: playwright-mcp
Version: 0.1.0
Summary: Playwright wrapper for MCP
Author-email: Shannon Sands <shannon.sands.1979@gmail.com>
Requires-Python: >=3.11
Requires-Dist: mcp>=1.3.0
Requires-Dist: playwright>=1.50.0
